buildbot_www/VERSION
buildbot_www/__init__.py
buildbot_www/static/browser-warning-list.js
buildbot_www/static/browser-warning.css
buildbot_www/static/browser-warning.js
buildbot_www/static/icon.png
buildbot_www/static/icon.svg
buildbot_www/static/index.html
buildbot_www/static/manifest.json
buildbot_www/static/robots.txt
buildbot_www/static/assets/index-CQKNRskk.css
buildbot_www/static/assets/index-D1Qujclx.js
buildbot_www-4.3.0.dist-info/METADATA
buildbot_www-4.3.0.dist-info/WHEEL
buildbot_www-4.3.0.dist-info/entry_points.txt
buildbot_www-4.3.0.dist-info/top_level.txt
buildbot_www-4.3.0.dist-info/RECORD
