Metadata-Version: 2.1
Name: buildbot-www
Version: 4.3.0
Summary: Buildbot UI
Home-page: http://buildbot.net/
Author: Povilas Kanapickas
Author-email: povilas@radix.lt
Classifier: License :: OSI Approved :: GNU General Public License v2 (GPLv2)
Requires-Dist: buildbot
